[{"TYPE":"KEY_WORD_CLASS","position":0,"lexem":"class"},{"TYPE":"ID","position":6,"lexem":"main"},{"TYPE":"OPEN_BRACE","position":11,"lexem":"{"},{"TYPE":"KEY_WORD_VAR","position":17,"lexem":"var"},{"TYPE":"TYPE_INT","position":21,"lexem":"INT"},{"TYPE":"ID","position":25,"lexem":"lol"},{"TYPE":"OPERATOR_ASSIGN","position":29,"lexem":"="},{"TYPE":"INT","position":31,"lexem":"50"},{"TYPE":"SEMI_COLON","position":33,"lexem":";"},{"TYPE":"KEY_WORD_CLASS","position":44,"lexem":"class"},{"TYPE":"ID","position":50,"lexem":"hello"},{"TYPE":"OPEN_BRACE","position":56,"lexem":"{"},{"TYPE":"KEY_WORD_VAR","position":66,"lexem":"var"},{"TYPE":"TYPE_INT","position":70,"lexem":"INT"},{"TYPE":"ID","position":74,"lexem":"i"},{"TYPE":"OPERATOR_ASSIGN","position":76,"lexem":"="},{"TYPE":"INT","position":78,"lexem":"50"},{"TYPE":"SEMI_COLON","position":80,"lexem":";"},{"TYPE":"KEY_WORD_RETURN","position":90,"lexem":"return"},{"TYPE":"ID","position":97,"lexem":"i"},{"TYPE":"SEMI_COLON","position":98,"lexem":";"},{"TYPE":"CLOSE_BRACE","position":104,"lexem":"}"},{"TYPE":"KEY_WORD_CLASS","position":111,"lexem":"class"},{"TYPE":"ID","position":117,"lexem":"hi"},{"TYPE":"OPEN_BRACE","position":120,"lexem":"{"},{"TYPE":"KEY_WORD_VAR","position":130,"lexem":"var"},{"TYPE":"TYPE_INT","position":134,"lexem":"INT"},{"TYPE":"ID","position":138,"lexem":"i"},{"TYPE":"OPERATOR_ASSIGN","position":140,"lexem":"="},{"TYPE":"INT","position":142,"lexem":"0"},{"TYPE":"SEMI_COLON","position":143,"lexem":";"},{"TYPE":"CLOSE_BRACE","position":149,"lexem":"}"},{"TYPE":"KEY_WORD_VAR","position":156,"lexem":"var"},{"TYPE":"TYPE_INT","position":160,"lexem":"INT"},{"TYPE":"ID","position":164,"lexem":"bca"},{"TYPE":"OPERATOR_ASSIGN","position":168,"lexem":"="},{"TYPE":"INT","position":170,"lexem":"12"},{"TYPE":"SEMI_COLON","position":172,"lexem":";"},{"TYPE":"KEY_WORD_VAR","position":179,"lexem":"var"},{"TYPE":"TYPE_INT","position":183,"lexem":"INT"},{"TYPE":"ID","position":187,"lexem":"abc"},{"TYPE":"OPERATOR_ASSIGN","position":191,"lexem":"="},{"TYPE":"ID","position":193,"lexem":"lol"},{"TYPE":"MATH_OP_PLUS","position":197,"lexem":"+"},{"TYPE":"ID","position":199,"lexem":"bca"},{"TYPE":"SEMI_COLON","position":202,"lexem":";"},{"TYPE":"KEY_WORD_VAR","position":208,"lexem":"var"},{"TYPE":"TYPE_INT","position":212,"lexem":"INT"},{"TYPE":"ID","position":216,"lexem":"bbb"},{"TYPE":"OPERATOR_ASSIGN","position":220,"lexem":"="},{"TYPE":"ID","position":222,"lexem":"lol"},{"TYPE":"MATH_OP_MINUS","position":226,"lexem":"-"},{"TYPE":"ID","position":228,"lexem":"bca"},{"TYPE":"SEMI_COLON","position":231,"lexem":";"},{"TYPE":"CLOSE_BRACE","position":233,"lexem":"}"}]